{"ongoing_trials": {}, "hyperparameters": {"space": [{"class_name": "Int", "config": {"name": "units", "default": null, "conditions": [], "min_value": 32, "max_value": 512, "step": 32, "sampling": null}}, {"class_name": "Choice", "config": {"name": "activation", "default": "relu", "conditions": [], "values": ["relu", "tanh"], "ordered": false}}, {"class_name": "Boolean", "config": {"name": "dropout", "default": false, "conditions": []}}, {"class_name": "Float", "config": {"name": "lr", "default": 0.0001, "conditions": [], "min_value": 0.0001, "max_value": 0.01, "step": null, "sampling": "log"}}], "values": {"units": 32, "activation": "relu", "dropout": false, "lr": 0.0001}}, "seed": 4099, "seed_state": 4111, "tried_so_far": ["1ecfcc3f28c2ffd675806aba56b7d23c", "5b019052bdd7f612f28829cec73ba59c", "79c2716b772413245917a546c43a55cf"]}